liblaf/melon/__init__.py
liblaf/melon/__init__.pyi
liblaf/melon/__main__.py
liblaf/melon/_version.py
liblaf/melon/_version.pyi
liblaf/melon/py.typed
liblaf/melon/_src/__init__.py
liblaf/melon/_src/__init__.pyi
liblaf/melon/_src/bounds.py
liblaf/melon/_src/edges.py
liblaf/melon/_src/geodesic.py
liblaf/melon/_src/graph.py
liblaf/melon/barycentric/__init__.py
liblaf/melon/barycentric/__init__.pyi
liblaf/melon/barycentric/_points.py
liblaf/melon/barycentric/_sample.py
liblaf/melon/cli/__init__.py
liblaf/melon/cli/__init__.pyi
liblaf/melon/cli/__main__.py
liblaf/melon/cli/_annotate_landmarks.py
liblaf/melon/cli/_app.py
liblaf/melon/cli/_convert.py
liblaf/melon/cli/_info.py
liblaf/melon/compat/__init__.py
liblaf/melon/compat/__init__.pyi
liblaf/melon/compat/_attributes.py
liblaf/melon/ext/__init__.py
liblaf/melon/ext/__init__.pyi
liblaf/melon/ext/_mesh_fix.py
liblaf/melon/ext/_tetwild.py
liblaf/melon/ext/wrap/__init__.py
liblaf/melon/ext/wrap/__init__.pyi
liblaf/melon/ext/wrap/_annotate_landmarks.py
liblaf/melon/ext/wrap/_fast_wrapping.py
liblaf/melon/ext/wrap/_templates.py
liblaf/melon/ext/wrap/templates/annotate-landmarks.wrap
liblaf/melon/ext/wrap/templates/fast-wrapping.wrap
liblaf/melon/io/__init__.py
liblaf/melon/io/__init__.pyi
liblaf/melon/io/_save.py
liblaf/melon/io/abc/__init__.py
liblaf/melon/io/abc/__init__.pyi
liblaf/melon/io/abc/_converter.py
liblaf/melon/io/abc/_reader.py
liblaf/melon/io/abc/_typing.py
liblaf/melon/io/abc/_writer.py
liblaf/melon/io/paraview/__init__.py
liblaf/melon/io/paraview/__init__.pyi
liblaf/melon/io/paraview/_pvd_writer.py
liblaf/melon/io/paraview/series/__init__.py
liblaf/melon/io/paraview/series/__init__.pyi
liblaf/melon/io/paraview/series/_reader.py
liblaf/melon/io/paraview/series/_shared.py
liblaf/melon/io/paraview/series/_writer.py
liblaf/melon/io/pyvista/__init__.py
liblaf/melon/io/pyvista/__init__.pyi
liblaf/melon/io/pyvista/_convert.py
liblaf/melon/io/pyvista/multi_block/__init__.py
liblaf_melon-1.1.1.dist-info/METADATA
liblaf_melon-1.1.1.dist-info/WHEEL
liblaf_melon-1.1.1.dist-info/entry_points.txt
liblaf_melon-1.1.1.dist-info/licenses/LICENSE
liblaf_melon-1.1.1.dist-info/RECORD
