Metadata-Version: 2.4
Name: liblaf-melon
Version: 1.1.1
Summary: 🍉 A comprehensive Python library for 3D mesh processing with advanced I/O capabilities, proximity analysis, and integration with external mesh processing tools.
Project-URL: Changelog, https://github.com/liblaf/melon/blob/main/CHANGELOG.md
Project-URL: Documentation, https://liblaf.github.io/melon/
Project-URL: Homepage, https://github.com/liblaf/melon
Project-URL: Issue Tracker, https://github.com/liblaf/melon/issues
Project-URL: Release Notes, https://github.com/liblaf/melon/releases
Project-URL: Source Code, https://github.com/liblaf/melon
Author-email: liblaf <30631553+liblaf@users.noreply.github.com>
License-Expression: MIT
License-File: LICENSE
Classifier: Development Status :: 4 - Beta
Classifier: Intended Audience :: Developers
Classifier: License :: OSI Approved
Classifier: License :: OSI Approved :: MIT License
Classifier: Operating System :: OS Independent
Classifier: Programming Language :: Python
Classifier: Programming Language :: Python :: 3
Classifier: Programming Language :: Python :: 3.12
Classifier: Programming Language :: Python :: 3.13
Classifier: Typing :: Typed
Requires-Python: >=3.12
Requires-Dist: attrs<26,>=25
Requires-Dist: cyclopts<5,>=4
Requires-Dist: einops<0.9,>=0.8
Requires-Dist: jax<0.10,>=0.9
Requires-Dist: jaxtyping<0.4,>=0.3
Requires-Dist: jinja2<4,>=3
Requires-Dist: lazy-loader<0.5,>=0.4
Requires-Dist: liblaf-grapes<10,>=9
Requires-Dist: meshio<6,>=5
Requires-Dist: more-itertools<11,>=10
Requires-Dist: networkx<4,>=3
Requires-Dist: numpy<3,>=2
Requires-Dist: polars<2,>=1
Requires-Dist: potpourri3d<2,>=1
Requires-Dist: pydantic<3,>=2
Requires-Dist: pydicom<4,>=3
Requires-Dist: pymeshfix<0.18,>=0.17
Requires-Dist: pyvista<0.47,>=0.46
Requires-Dist: rich<15,>=14
Requires-Dist: scipy<2,>=1
Requires-Dist: trimesh[easy]<5,>=4
Requires-Dist: warp-lang<2,>=1
Provides-Extra: cuda12
Requires-Dist: jax[cuda12]<0.10,>=0.9; extra == 'cuda12'
Provides-Extra: cuda13
Requires-Dist: jax[cuda13]<0.10,>=0.9; extra == 'cuda13'
